innovation_serviceauth/__init__.py
innovation_serviceauth/client.py
innovation_serviceauth/constants.py
innovation_serviceauth-1.0.0.dist-info/LICENSE.txt
innovation_serviceauth-1.0.0.dist-info/METADATA
innovation_serviceauth-1.0.0.dist-info/WHEEL
innovation_serviceauth-1.0.0.dist-info/top_level.txt
innovation_serviceauth-1.0.0.dist-info/RECORD
