Metadata-Version: 2.1
Name: innovation-serviceauth
Version: 1.0.0
Summary: This package is an Indico Innovation IAM gRPC client to be imported by Indico Innovation API clients.
Home-page: https://github.com/INDICO-INNOVATION/indico_service_auth_python
Author: Indico Innovation
Author-email: dev@indicoinnovation.pt
License: Apache License
Requires-Python: >=3.10
License-File: LICENSE.txt
Requires-Dist: grpcio ==1.54.2
Requires-Dist: grpcio-tools ==1.54.2
Requires-Dist: jwcrypto ==1.5.0
